setup.py
daemonfixture/__init__.py
daemonfixture/daemon.py
daemonfixture.egg-info/PKG-INFO
daemonfixture.egg-info/SOURCES.txt
daemonfixture.egg-info/dependency_links.txt
daemonfixture.egg-info/requires.txt
daemonfixture.egg-info/top_level.txt
daemonfixture/tests/__init__.py
daemonfixture/tests/test_daemon.py