Metadata-Version: 1.0
Name: daemonfixture
Version: 0.1.0
Summary: Fixture for starting and stopping daemon processes in tests
Home-page: http://launchpad.net/daemonfixture
Author: Free Ekanayaka
Author-email: <free.ekanayaka@canonical.com>
License: AGPL
Keywords: fixtures subprocess
Platform: UNKNOWN
